aiida_wien2k/__init__.py
aiida_wien2k/calculations/run123_lapw.py
aiida_wien2k/configs/codes/run123_lapw.yml
aiida_wien2k/configs/computers/localhost.yml
aiida_wien2k/parsers/scf123.py
aiida_wien2k/workflows/scf123_workchain.py
aiida_wien2k-0.2.0.dist-info/entry_points.txt
aiida_wien2k-0.2.0.dist-info/LICENSE
aiida_wien2k-0.2.0.dist-info/WHEEL
aiida_wien2k-0.2.0.dist-info/METADATA
aiida_wien2k-0.2.0.dist-info/RECORD
