Metadata-Version: 2.1
Name: aiida-wien2k
Version: 0.2.0
Summary: The official AiiDA plugin for WIEN2k.
Keywords: aiida,workflows
Author-email: The AiiDA team <developers@aiida.net>
Requires-Python: >=3.8
Classifier: Development Status :: 5 - Production/Stable
Classifier: Framework :: AiiDA
Classifier: License :: OSI Approved :: MIT License
Classifier: Programming Language :: Python
Classifier: Programming Language :: Python :: 3.8
Classifier: Programming Language :: Python :: 3.9
Classifier: Programming Language :: Python :: 3.10
Classifier: Programming Language :: Python :: 3.11
Classifier: Programming Language :: Python :: 3.12
Requires-Dist: aiida_core[atomic_tools]~=2.0
Requires-Dist: fuzzywuzzy~=0.18.0
Requires-Dist: pgtest~=1.3 ; extra == "dev"
Requires-Dist: pre-commit~=2.2 ; extra == "dev"
Requires-Dist: pytest-regressions~=2.0 ; extra == "dev"
Provides-Extra: dev
